hisar/__init__.py
hisar/cli.py
hisar/main.py
hisar/report.py
hisar/utils.py
hisar/ws.py
hisar-0.1.0.dist-info/METADATA
hisar-0.1.0.dist-info/WHEEL
hisar-0.1.0.dist-info/entry_points.txt
hisar-0.1.0.dist-info/RECORD
