Metadata-Version: 2.1
Name: hisar
Version: 0.1.0
Summary: A load testing tool
Author: walidsa3d
Requires-Python: >=3.10,<4.0
Classifier: Programming Language :: Python :: 3
Classifier: Programming Language :: Python :: 3.10
Classifier: Programming Language :: Python :: 3.11
Classifier: Programming Language :: Python :: 3.12
Classifier: Programming Language :: Python :: 3.13
Requires-Dist: click (>=8.1.3,<9.0.0)
Requires-Dist: httpx (>=0.27.2,<0.28.0)
Requires-Dist: jinja2 (>=3.1.4,<4.0.0)
Requires-Dist: rich (>=13.9.2,<14.0.0)
Requires-Dist: uvloop (>=0.21.0,<0.22.0)
